toolwiki/__init__.py
toolwiki/page.py
toolwiki/tables.py
toolwiki-0.1.18.dist-info/LICENSE
toolwiki-0.1.18.dist-info/METADATA
toolwiki-0.1.18.dist-info/WHEEL
toolwiki-0.1.18.dist-info/top_level.txt
toolwiki-0.1.18.dist-info/RECORD
