Metadata-Version: 2.1
Name: toolwiki
Version: 0.1.18
Summary: A python library to extract information from Wikipedia pages.
Home-page: https://github.com/santoshbs/toolwiki
Author: Santosh Srinivas
Author-email: santosh.b.srinivas@outlook.com
License: MIT
Keywords: python,html table rowspan colspan,scrape parse extract,dataframe
Platform: UNKNOWN
Classifier: Programming Language :: Python :: 3
Classifier: Programming Language :: Python :: 3.6
Classifier: Programming Language :: Python :: 3.7
Classifier: Programming Language :: Python :: 3.8
Classifier: Programming Language :: Python :: 3.9
Classifier: License :: OSI Approved :: MIT License
Classifier: Operating System :: OS Independent
License-File: LICENSE
Requires-Dist: numpy
Requires-Dist: pandas
Requires-Dist: beautifulsoup4
Requires-Dist: lxml
Requires-Dist: spacy
